pyquicktest/__init__.py
pyquicktest/assertions.py
pyquicktest/authorship.py
pyquicktest/cli.py
pyquicktest/decorators.py
pyquicktest/gen.py
pyquicktest/pqt.py
pyquicktest/rewrite.py
pyquicktest/utils.py
PyQuickTest-0.1.0.dist-info/LICENSE
PyQuickTest-0.1.0.dist-info/METADATA
PyQuickTest-0.1.0.dist-info/WHEEL
PyQuickTest-0.1.0.dist-info/entry_points.txt
PyQuickTest-0.1.0.dist-info/top_level.txt
PyQuickTest-0.1.0.dist-info/RECORD
