Metadata-Version: 2.1
Name: PyQuickTest
Version: 0.1.0
Summary: PyQuickTest is an experimental python testing framework designed to                            deliver an easy-and-quick-to-start python testing mechanism.
Home-page: https://github.com/quentinemusee/PyQuickTest
Download-URL: https://pypi.org/project/pyquicktest/
Author: Quentin Raimbaud
Author-email: quentin.raimbaud.contact@gmail.com
License: PSFL
Keywords: Code testing,Experimental,Testing framework
Classifier: Development Status :: 3 - Alpha
Classifier: Topic :: Utilities
Classifier: License :: OSI Approved :: GNU General Public License (GPL)
License-File: LICENSE
Requires-Dist: colorama
